core/__init__.py
core/config.py
core/logger.py
core/requests.py
core/retry.py
core/security.py
core/validators.py
core/exceptions/__init__.py
core/exceptions/api.py
core/exceptions/decorators.py
core/exceptions/resource.py
schemas/__init__.py
schemas/contacts.py
schemas/errors.py
schemas/messages.py
schemas/webhook.py
sdk/__init__.py
sdk/client.py
sdk/features/__init__.py
sdk/features/contacts.py
sdk/features/messages.py
server/__init__.py
server/app.py
messaging_py_sdk-2.1.2.dist-info/METADATA
messaging_py_sdk-2.1.2.dist-info/WHEEL
messaging_py_sdk-2.1.2.dist-info/top_level.txt
messaging_py_sdk-2.1.2.dist-info/RECORD
