Metadata-Version: 2.1
Name: messaging-py-sdk
Version: 2.1.2
Summary: A Python SDK for managing messages and contacts, with webhook integration.
Home-page: https://github.com/shiningflash/messaging-sdk
Author: Amirul Islam
Author-email: amirulislamalmamun@gmail.com
License: Apache
Project-URL: Documentation, https://github.com/shiningflash/messaging-sdk/blob/main/README.md
Project-URL: Source Code, https://github.com/shiningflash
Project-URL: Issue Tracker, https://github.com/shiningflash/messaging-sdk/issues
Keywords: messaging sdk python api contacts
Classifier: Programming Language :: Python :: 3.8
Classifier: Programming Language :: Python :: 3.9
Classifier: Programming Language :: Python :: 3.10
Classifier: Programming Language :: Python :: 3.11
Classifier: Programming Language :: Python :: 3.12
Classifier: Operating System :: OS Independent
Classifier: Intended Audience :: Developers
Classifier: Topic :: Software Development :: Libraries :: Python Modules
Requires-Python: >=3.8
Requires-Dist: requests
Requires-Dist: python-dotenv
Requires-Dist: pytest
Requires-Dist: pytest-mock
Requires-Dist: flake8
Requires-Dist: black
Requires-Dist: mypy
Requires-Dist: pydantic
Requires-Dist: pytest-cov
Requires-Dist: fastapi
Requires-Dist: uvicorn
Requires-Dist: pytest-asyncio
Requires-Dist: httpx
Requires-Dist: pydantic-settings
Provides-Extra: dev
Requires-Dist: flake8; extra == "dev"
Requires-Dist: black; extra == "dev"
Requires-Dist: mypy; extra == "dev"
Requires-Dist: pytest; extra == "dev"
Requires-Dist: pytest-cov; extra == "dev"
Requires-Dist: pytest-asyncio; extra == "dev"
Requires-Dist: pytest-mock; extra == "dev"
